spritekit/__init__.py
spritekit/_drawable.py
spritekit/_glfw.py
spritekit/_renderer.py
spritekit/actions.py
spritekit/actor.py
spritekit/audio.py
spritekit/cache.py
spritekit/camera.py
spritekit/easing.py
spritekit/emitter.py
spritekit/fsm.py
spritekit/label.py
spritekit/main.py
spritekit/math.py
spritekit/matrix.py
spritekit/physics.py
spritekit/quaternion.py
spritekit/raylib.py
spritekit/scene.py
spritekit/shader.py
spritekit/shapes.py
spritekit/sprite.py
spritekit/state.py
spritekit/texture.py
spritekit/timer.py
spritekit/vector.py
spritekit/window.py
spritekit/__pycache__/__init__.cpython-312.pyc
spritekit/__pycache__/_drawable.cpython-312.pyc
spritekit/__pycache__/_glfw.cpython-312.pyc
spritekit/__pycache__/_renderer.cpython-312.pyc
spritekit/__pycache__/actions.cpython-312.pyc
spritekit/__pycache__/actor.cpython-312.pyc
spritekit/__pycache__/audio.cpython-312.pyc
spritekit/__pycache__/cache.cpython-312.pyc
spritekit/__pycache__/camera.cpython-312.pyc
spritekit/__pycache__/easing.cpython-312.pyc
spritekit/__pycache__/emitter.cpython-312.pyc
spritekit/__pycache__/label.cpython-312.pyc
spritekit/__pycache__/main.cpython-312.pyc
spritekit/__pycache__/scene.cpython-312.pyc
spritekit/__pycache__/shader.cpython-312.pyc
spritekit/__pycache__/shapes.cpython-312.pyc
spritekit/__pycache__/sprite.cpython-312.pyc
spritekit/__pycache__/state.cpython-312.pyc
spritekit/__pycache__/timer.cpython-312.pyc
spritekit/__pycache__/window.cpython-312.pyc
spritekit-0.2.2.dist-info/licenses/LICENSE
spritekit-0.2.2.dist-info/METADATA
spritekit-0.2.2.dist-info/WHEEL
spritekit-0.2.2.dist-info/top_level.txt
spritekit-0.2.2.dist-info/RECORD
