Metadata-Version: 2.4
Name: spritekit
Version: 0.2.2
Summary: 2D scene+actor framework built on top of raylib
Home-page: https://github.com/takeiteasy/PySpriteKit
Author: George Watson
Author-email: George Watson <gigolo@hotmail.co.uk>
Project-URL: Homepage, https://github.com/takeiteasy/PySpriteKit
Project-URL: Issues, https://github.com/takeiteasy/PySpriteKit/issues
Classifier: Programming Language :: Python :: 3
Classifier: License :: OSI Approved :: MIT License
Classifier: Operating System :: OS Independent
Requires-Python: >=3.10
License-File: LICENSE
Requires-Dist: transitions==0.9.2
Requires-Dist: pyglm==2.8.1
Requires-Dist: raudio==0.0.1
Requires-Dist: moderngl==5.12.0
Requires-Dist: numpy==2.2.4
Requires-Dist: pillow==11.1.0
Requires-Dist: pyglsl==0.0.8
Dynamic: author
Dynamic: home-page
Dynamic: license-file
